{
    "project": {
        "name": "test help file",
        "default-file": "file.html"
    },

    "menu": [
        ["item name", "file.md"],
        ["item name", "file.md"],
        ["item name", "file.md", [
            ["item name", "file.md"],
            ["item name", "file.md"],
            ["item name", "file.md"]
        ]],
        ["item name", [
            ["item name", "file.md"],
            ["item name", "file.md"],
            ["item name", "file.md"]
        ]]
    ],

    "files": [
        "file.md"
    ]
}